CHANGES.txt
LICENSE.txt
MANIFEST.in
README.txt
setup.py
PlayingCards.egg-info/PKG-INFO
PlayingCards.egg-info/SOURCES.txt
PlayingCards.egg-info/dependency_links.txt
PlayingCards.egg-info/top_level.txt
bin/interface.py
playingcards/__init__.py
playingcards/pcards.py
playingcards/test/__init__.py
playingcards/test/test_pcards.py