Metadata-Version: 1.0
Name: PlayingCards
Version: 0.1.2
Summary: A module to create card games and playing card simulations.
Home-page: UNKNOWN
Author: Paritosh Mathur
Author-email: admin@parrymathur.com
License: LICENSE.txt
Platform: UNKNOWN
